[{"scene_id": "bb-10-21-05s0", "raw": "a woman is talking about a woman who is sitting down.", "with_names": ""}, {"scene_id": "bb-10-21-05s1", "raw": "a group of people are having a conversation in a room.", "with_names": "a group of people are having a conversation in a room."}, {"scene_id": "bb-10-21-05s2", "raw": "a man and woman are sitting on a couch and a man is laughing.", "with_names": ""}, {"scene_id": "bb-10-21-05s3", "raw": "a man is talking about a conference and then a man is shown sitting in a chair.", "with_names": ""}, {"scene_id": "bb-10-21-05s4", "raw": "a man and woman are shown kissing each other in a room.", "with_names": "a man and woman are shown kissing each other in a room."}, {"scene_id": "bb-10-21-05s5", "raw": "a family is enjoying themselves in a living room and they are having a conversation.", "with_names": "a family is enjoying themselves in a living room and they are having a conversation."}, {"scene_id": "bb-10-21-05s6", "raw": "a man and woman are talking about a man and a woman is talking.", "with_names": ""}, {"scene_id": "bb-10-21-05s7", "raw": "a woman is walking around a room and then a man is talking.", "with_names": ""}, {"scene_id": "bb-10-21-05s8", "raw": "a woman is talking about a man and then a man is shown dancing.", "with_names": ""}, {"scene_id": "bb-10-21-05s9", "raw": "a woman is talking about a woman who is being interviewed.", "with_names": ""}]