[{"scene_id": "bb-03-01-07s0", "raw": "a woman is laying on a bed and a man is tickling her.", "with_names": "a woman is laying on a bed and a man is tickling her."}, {"scene_id": "bb-03-01-07s1", "raw": "a man and a woman are walking around in a living room.", "with_names": ""}, {"scene_id": "bb-03-01-07s2", "raw": "a man is talking about a woman and then a man is laughing.", "with_names": ""}, {"scene_id": "bb-03-01-07s3", "raw": "a man and a woman are talking about a restaurant.", "with_names": ""}, {"scene_id": "bb-03-01-07s4", "raw": "a man is talking about a woman and then a man is shown walking around a room.", "with_names": ""}, {"scene_id": "bb-03-01-07s5", "raw": "a man is tickling a man on the couch and the other man is laughing.", "with_names": "a man is tickling a man on the couch and the other man is laughing."}, {"scene_id": "bb-03-01-07s6", "raw": "a woman is talking about a man and then a woman is shown talking about it.", "with_names": ""}, {"scene_id": "bb-03-01-07s7", "raw": "a woman is talking about her experience and then a man is shown sitting down.", "with_names": ""}, {"scene_id": "bb-03-01-07s8", "raw": "a man is sleeping and another man is sleeping in a dark room.", "with_names": "Nick is sleeping and another man is sleeping in a dark room."}, {"scene_id": "bb-03-01-07s9", "raw": "a woman is swimming in a pool and a man is talking.", "with_names": ""}, {"scene_id": "bb-03-01-07s10", "raw": "", "with_names": ""}]