[{"scene_id": "bb-04-28-16s0", "raw": "A scene from a TV show in which a woman is wearing a purple dress and a man is in a suit.", "with_names": "Quinn is wearing a purple dress and Liam is in a suit."}, {"scene_id": "bb-04-28-16s1", "raw": "A scene from a TV show in which a young black man is looking at the camera with a confused expression.", "with_names": "a young black man is looking at the camera with a confused expression."}, {"scene_id": "bb-04-28-16s2", "raw": "", "with_names": ""}, {"scene_id": "bb-04-28-16s3", "raw": "", "with_names": ""}, {"scene_id": "bb-04-28-16s4", "raw": "", "with_names": ""}, {"scene_id": "bb-04-28-16s5", "raw": "", "with_names": ""}, {"scene_id": "bb-04-28-16s6", "raw": "", "with_names": ""}, {"scene_id": "bb-04-28-16s7", "raw": "A scene from a TV show in which a woman is talking about her breast cancer diagnosis.", "with_names": ""}, {"scene_id": "bb-04-28-16s8", "raw": "A scene from a TV show in which a woman is wearing a red, white and blue dress.", "with_names": "a woman is wearing a red, white and blue dress."}, {"scene_id": "bb-04-28-16s9", "raw": "", "with_names": ""}, {"scene_id": "bb-04-28-16s10", "raw": "", "with_names": ""}, {"scene_id": "bb-04-28-16s11", "raw": "", "with_names": ""}, {"scene_id": "bb-04-28-16s12", "raw": "A scene from a TV show in which a man is bent over a desk, his head down, and his hands on the desk.", "with_names": "a man is bent over a desk, his head down, and his hands on the desk."}, {"scene_id": "bb-04-28-16s13", "raw": "", "with_names": ""}, {"scene_id": "bb-04-28-16s14", "raw": "", "with_names": ""}]