[{"scene_id": "oltl-06-09-09s0", "raw": "", "with_names": ""}, {"scene_id": "oltl-06-09-09s1", "raw": "", "with_names": ""}, {"scene_id": "oltl-06-09-09s2", "raw": "a man and woman are having a conversation about a restaurant.", "with_names": "a man and woman are having a conversation about a restaurant."}, {"scene_id": "oltl-06-09-09s3", "raw": "a woman is talking to a man and then a woman is shown talking.", "with_names": ""}, {"scene_id": "oltl-06-09-09s4", "raw": "a man and a woman are laughing and laughing at each other.", "with_names": "Todd and Blair are laughing and laughing at each other."}, {"scene_id": "oltl-06-09-09s5", "raw": "a man and woman are talking about a man and she is laughing.", "with_names": ""}, {"scene_id": "oltl-06-09-09s6", "raw": "a man and woman are talking about a man and then they are kissing.", "with_names": ""}, {"scene_id": "oltl-06-09-09s7", "raw": "a man and woman are in a kitchen and they are doing a meal.", "with_names": "a man and woman are in a kitchen and they are doing a meal."}, {"scene_id": "oltl-06-09-09s8", "raw": "a man and woman are talking about a man and then a man is laughing.", "with_names": ""}, {"scene_id": "oltl-06-09-09s9", "raw": "a woman is talking about a hospital and another woman is shown.", "with_names": ""}, {"scene_id": "oltl-06-09-09s10", "raw": "a man and woman are talking about a man and then a man is talking.", "with_names": ""}, {"scene_id": "oltl-06-09-09s11", "raw": "a man and woman are talking about a man and she is laughing.", "with_names": ""}, {"scene_id": "oltl-06-09-09s12", "raw": "a man and woman are talking about a man and the man is laughing.", "with_names": ""}, {"scene_id": "oltl-06-09-09s13", "raw": "a man and woman are talking about a man and he is laughing.", "with_names": ""}, {"scene_id": "oltl-06-09-09s14", "raw": "a man is walking around a room with other people.", "with_names": ""}, {"scene_id": "oltl-06-09-09s15", "raw": "a woman is talking about a man and then a woman is shown laughing.", "with_names": ""}, {"scene_id": "oltl-06-09-09s16", "raw": "a man and a woman are talking about a man.", "with_names": ""}, {"scene_id": "oltl-06-09-09s17", "raw": "a man and woman are sitting at a table eating and talking.", "with_names": ""}, {"scene_id": "oltl-06-09-09s18", "raw": "a woman is walking around a dining room and then the man enters the room.", "with_names": ""}, {"scene_id": "oltl-06-09-09s19", "raw": "a woman is talking to a man and then a woman is shown.", "with_names": ""}, {"scene_id": "oltl-06-09-09s20", "raw": "a man is walking through a room and then a man is sitting down and the man is laughing.", "with_names": "a man is walking through a room and then a man is sitting down and the man is laughing."}, {"scene_id": "oltl-06-09-09s21", "raw": "a man and a woman are talking about a topic.", "with_names": ""}, {"scene_id": "oltl-06-09-09s22", "raw": "a man and a woman are sitting down and talking to each other.", "with_names": ""}, {"scene_id": "oltl-06-09-09s23", "raw": "a man is talking about a woman and then a man is shown kissing her.", "with_names": ""}, {"scene_id": "oltl-06-09-09s24", "raw": "a woman is talking to another woman and then she is laughing.", "with_names": ""}, {"scene_id": "oltl-06-09-09s25", "raw": "a man and a woman are sitting down and laughing.", "with_names": "Todd and Blair are sitting down and laughing."}, {"scene_id": "oltl-06-09-09s26", "raw": "a man and woman are talking about a man and then she is laughing.", "with_names": ""}, {"scene_id": "oltl-06-09-09s27", "raw": "a man and woman are talking about a topic and the man is laughing.", "with_names": ""}, {"scene_id": "oltl-06-09-09s28", "raw": "a man and a woman are standing in front of a camera and they are talking.", "with_names": ""}, {"scene_id": "oltl-06-09-09s29", "raw": "a man and a woman are talking about a topic.", "with_names": ""}, {"scene_id": "oltl-06-09-09s30", "raw": "a man and a woman are sitting at a table and talking about a game.", "with_names": ""}, {"scene_id": "oltl-06-09-09s31", "raw": "a man and woman are talking about a topic and they are laughing.", "with_names": ""}, {"scene_id": "oltl-06-09-09s32", "raw": "a man and woman are sitting at a table and having a conversation.", "with_names": "a man and woman are sitting at a table and having a conversation."}, {"scene_id": "oltl-06-09-09s33", "raw": "a man and woman are talking about a man and he is laughing.", "with_names": ""}, {"scene_id": "oltl-06-09-09s34", "raw": "a woman is talking about a woman who is sitting down.", "with_names": ""}, {"scene_id": "oltl-06-09-09s35", "raw": "a group of people are walking around and kissing each other.", "with_names": ""}, {"scene_id": "oltl-06-09-09s36", "raw": "a man and a woman are talking about a romantic conversation.", "with_names": ""}, {"scene_id": "oltl-06-09-09s37", "raw": "a man and woman are in a room and they are having a great time.", "with_names": "Schuyler and woman are in a room and they are having a great time."}, {"scene_id": "oltl-06-09-09s38", "raw": "a man and a woman are drinking wine and talking about it.", "with_names": ""}, {"scene_id": "oltl-06-09-09s39", "raw": "a man and woman are in a room and they are having a conversation.", "with_names": "a man and woman are in a room and they are having a conversation."}, {"scene_id": "oltl-06-09-09s40", "raw": "", "with_names": ""}, {"scene_id": "oltl-06-09-09s41", "raw": "a man and a woman are talking about a conversation.", "with_names": ""}]